components/__init__.py
components/groups.py
dependencies/__init__.py
dependencies/invenio-communities/AUTHORS.rst
dependencies/invenio-communities/CHANGES.rst
dependencies/invenio-communities/CONTRIBUTING.rst
dependencies/invenio-communities/INSTALL.rst
dependencies/invenio-communities/MANIFEST.in
dependencies/invenio-communities/README.rst
dependencies/invenio-communities/pyproject.toml
dependencies/invenio-communities/run-js-linter.sh
dependencies/invenio-communities/run-tests.sh
dependencies/invenio-communities/setup.py
dependencies/invenio-communities/docs/api.rst
dependencies/invenio-communities/docs/authors.rst
dependencies/invenio-communities/docs/changes.rst
dependencies/invenio-communities/docs/conf.py
dependencies/invenio-communities/docs/contributing.rst
dependencies/invenio-communities/docs/index.rst
dependencies/invenio-communities/docs/installation.rst
dependencies/invenio-communities/docs/license.rst
dependencies/invenio-communities/docs/requirements.txt
dependencies/invenio-communities/docs/usage.rst
dependencies/invenio-communities/invenio_communities/__init__.py
dependencies/invenio-communities/invenio_communities/cli.py
dependencies/invenio-communities/invenio_communities/config.py
dependencies/invenio-communities/invenio_communities/errors.py
dependencies/invenio-communities/invenio_communities/ext.py
dependencies/invenio-communities/invenio_communities/generators.py
dependencies/invenio-communities/invenio_communities/permissions.py
dependencies/invenio-communities/invenio_communities/proxies.py
dependencies/invenio-communities/invenio_communities/roles.py
dependencies/invenio-communities/invenio_communities/searchapp.py
dependencies/invenio-communities/invenio_communities/tasks.py
dependencies/invenio-communities/invenio_communities/utils.py
dependencies/invenio-communities/invenio_communities/webpack.py
dependencies/invenio-communities/invenio_communities/administration/__init__.py
invenio_remote_user_data_kcworks-0.5.6b0.dist-info/LICENSE
invenio_remote_user_data_kcworks-0.5.6b0.dist-info/METADATA
invenio_remote_user_data_kcworks-0.5.6b0.dist-info/WHEEL
invenio_remote_user_data_kcworks-0.5.6b0.dist-info/entry_points.txt
invenio_remote_user_data_kcworks-0.5.6b0.dist-info/top_level.txt
invenio_remote_user_data_kcworks-0.5.6b0.dist-info/RECORD
