Metadata-Version: 2.1
Name: invenio-remote-user-data-kcworks
Version: 0.5.6b0
Summary: An extension to draw user data from remote sources into the Knowledge Commons Works InvenioRDM instance
Author-email: Mesh Research <scottia4@msu.edu>
License: MIT License
Project-URL: Homepage, https://github.com/MESH-Research/invenio-remote-user-data-kcworks
Keywords: invenio,inveniordm,users,research
Classifier: License :: OSI Approved :: MIT License
Classifier: Development Status :: 4 - Beta
Classifier: Programming Language :: Python
Classifier: Programming Language :: Python :: 3
Classifier: Programming Language :: Python :: 3.9
Classifier: Environment :: Web Environment
Classifier: Intended Audience :: Developers
Classifier: Operating System :: OS Independent
Classifier: Topic :: Internet :: WWW/HTTP :: Dynamic Content
Classifier: Topic :: Software Development :: Libraries :: Python Modules
Requires-Python: >=3.9
License-File: LICENSE
Requires-Dist: celery
Requires-Dist: click
Requires-Dist: deepdiff
Requires-Dist: invenio-app-rdm[opensearch2]<13.0.0
Requires-Dist: invenio-queues
Requires-Dist: invenio-search
Requires-Dist: invenio-utilities-tuw
Requires-Dist: opensearch-dsl
Provides-Extra: dev
Requires-Dist: check-manifest; extra == "dev"
Requires-Dist: pipenv; extra == "dev"
Requires-Dist: pip-tools; extra == "dev"
Requires-Dist: pytest>=7.3.2; extra == "dev"
Requires-Dist: pytest-invenio; extra == "dev"
Requires-Dist: pytest-runner; extra == "dev"
Requires-Dist: requests-mock; extra == "dev"
Provides-Extra: test
Requires-Dist: coverage; extra == "test"
